MountPenglai/__init__.py
MountPenglai-0.0.3.2.dist-info/METADATA
MountPenglai-0.0.3.2.dist-info/WHEEL
MountPenglai-0.0.3.2.dist-info/top_level.txt
MountPenglai-0.0.3.2.dist-info/RECORD
