Metadata-Version: 2.1
Name: MountPenglai
Version: 0.0.3.2
Home-page: https://github.com/RMSHE-MSH/Python-Homework-Open-Source-Project
Author: RMSHE
Author-email: asdfghjkl851@outlook.com
